LICENSE
MANIFEST.in
README.md
pyproject.toml
setup.py
src/searchbot/__init__.py
src/searchbot/bot.py
src/searchbot/rag.py
src/searchbot/retriever.py
src/searchbot/template.py
src/searchbot.egg-info/PKG-INFO
src/searchbot.egg-info/SOURCES.txt
src/searchbot.egg-info/dependency_links.txt
src/searchbot.egg-info/requires.txt
src/searchbot.egg-info/top_level.txt